_cadbiom.so
cadbiom/__init__.py
cadbiom/commons.py
cadbiom/models/__init__.py
cadbiom/models/biosignal/__init__.py
cadbiom/models/biosignal/sig_expr.py
cadbiom/models/biosignal/translators/TestExprCompiler.py
cadbiom/models/biosignal/translators/__init__.py
cadbiom/models/biosignal/translators/gt_visitors.py
cadbiom/models/biosignal/translators/sigexpr_compiler.py
cadbiom/models/biosignal/translators/sigexpr_lexer.py
cadbiom/models/clause_constraints/CLDynSys.py
cadbiom/models/clause_constraints/TestCLDynSys.py
cadbiom/models/clause_constraints/__init__.py
cadbiom/models/clause_constraints/mcl/CLUnfolder.py
cadbiom/models/clause_constraints/mcl/MCLAnalyser.py
cadbiom/models/clause_constraints/mcl/MCLQuery.py
cadbiom/models/clause_constraints/mcl/MCLSolutions.py
cadbiom/models/clause_constraints/mcl/MCLTranslators.py
cadbiom/models/clause_constraints/mcl/TestCLUnfolder.py
cadbiom/models/clause_constraints/mcl/TestMCLAnalyser.py
cadbiom/models/clause_constraints/mcl/TestMCLTranslators.py
cadbiom/models/clause_constraints/mcl/__init__.py
cadbiom/models/guard_transitions/TestModelExtraction.py
cadbiom/models/guard_transitions/__init__.py
cadbiom/models/guard_transitions/chart_model.py
cadbiom/models/guard_transitions/condexpLexer.py
cadbiom/models/guard_transitions/condexpParser.py
cadbiom/models/guard_transitions/extract_visitor.py
cadbiom/models/guard_transitions/analyser/TestStaticAnalysis.py
cadbiom/models/guard_transitions/analyser/__init__.py
cadbiom/models/guard_transitions/analyser/ana_visitors.py
cadbiom/models/guard_transitions/analyser/model_corrections.py
cadbiom/models/guard_transitions/analyser/static_analysis.py
cadbiom/models/guard_transitions/simulator/__init__.py
cadbiom/models/guard_transitions/simulator/chart_simul.py
cadbiom/models/guard_transitions/simulator/chart_simul_elem.py
cadbiom/models/guard_transitions/simulator/input_stream.py
cadbiom/models/guard_transitions/simulator/simul_aux.py
cadbiom-0.3.dist-info/METADATA
cadbiom-0.3.dist-info/RECORD
cadbiom-0.3.dist-info/WHEEL
cadbiom-0.3.dist-info/top_level.txt
